real_headers/__init__.py
real_headers/cli.py
real_headers/headers.py
real_headers/user_agents.py
real_headers-0.1.2.dist-info/LICENSE
real_headers-0.1.2.dist-info/METADATA
real_headers-0.1.2.dist-info/WHEEL
real_headers-0.1.2.dist-info/entry_points.txt
real_headers-0.1.2.dist-info/top_level.txt
real_headers-0.1.2.dist-info/RECORD
