Metadata-Version: 2.1
Name: real_headers
Version: 0.1.2
Summary: Real Headers is a Python library that generates random HTTP headers and browser fingerprints that mimic real browsers.
Home-page: https://github.com/iNadeemDev/real_headers
Author: Muhammad Nadeem
Author-email: nadeemdsb5@gmail.com
Project-URL: Source, https://github.com/iNadeemDev/real_headers
Keywords: headers,user-agent,browser,fingerprint,fake headers,real headers,request headers,http headers,random headers,realheaders
Classifier: Development Status :: 4 - Beta
Classifier: Programming Language :: Python
Classifier: Programming Language :: Python :: 2
Classifier: Programming Language :: Python :: 3
Classifier: Intended Audience :: Developers
Classifier: Topic :: Software Development :: Libraries
Classifier: Topic :: Software Development :: Libraries :: Python Modules
Classifier: Topic :: Internet :: WWW/HTTP :: Browsers
Classifier: License :: OSI Approved :: MIT License
Classifier: Operating System :: OS Independent
License-File: LICENSE
